sylviorus/__init__.py
sylviorus-2.1.dist-info/LICENSE
sylviorus-2.1.dist-info/METADATA
sylviorus-2.1.dist-info/WHEEL
sylviorus-2.1.dist-info/top_level.txt
sylviorus-2.1.dist-info/RECORD
