Metadata-Version: 2.1
Name: sylviorus
Version: 2.1
Summary: Sylviorus Wrapper
Home-page: https://github.com/NksamaX/Syl-Py.git
Author: NkSamaX
Author-email: noobanon@pm.me
License: License :: OSI Approved :: GNU Lesser General Public License v3 (LGPLv3)
Platform: UNKNOWN
Classifier: Development Status :: 4 - Beta
Classifier: Programming Language :: Python :: 3.6
Classifier: Programming Language :: Python :: 3.7
Classifier: Programming Language :: Python :: Implementation :: CPython
Classifier: Typing :: Typed
Requires-Python: >=3.6
License-File: LICENSE
Requires-Dist: requests (>=2.20)
